axisdb/__init__.py
axisdb/api.py
axisdb/errors.py
axisdb/cli/__init__.py
axisdb/engine/__init__.py
axisdb/engine/keycodec.py
axisdb/engine/locking.py
axisdb/engine/storage.py
axisdb/index/__init__.py
axisdb/index/fields.py
axisdb/index/prefix.py
axisdb/query/__init__.py
axisdb/query/ast.py
axisdb/query/eval.py
axisdb/server/__init__.py
axisdb/server/app.py
axisdb/server/schemas.py
axisdb-1.0.6.dist-info/licenses/LICENSE
axisdb-1.0.6.dist-info/METADATA
axisdb-1.0.6.dist-info/WHEEL
axisdb-1.0.6.dist-info/top_level.txt
axisdb-1.0.6.dist-info/RECORD
