Metadata-Version: 2.4
Name: axisdb
Version: 1.0.6
Summary: Tiny embedded document database for Python with N-dimensional coordinate keys.
Author: Oliver Ernster
License-Expression: GPL-3.0-only
Project-URL: Homepage, https://github.com/oernster/AxisDB
Project-URL: Repository, https://github.com/oernster/AxisDB
Project-URL: Issues, https://github.com/oernster/AxisDB/issues
Keywords: database,embedded,json,storage,coordinates,multidimensional
Classifier: Development Status :: 5 - Production/Stable
Classifier: Programming Language :: Python :: 3
Classifier: Programming Language :: Python :: 3.11
Classifier: Operating System :: OS Independent
Requires-Python: >=3.11
License-File: LICENSE
Requires-Dist: portalocker>=2.0.0
Provides-Extra: server
Requires-Dist: fastapi; extra == "server"
Requires-Dist: uvicorn; extra == "server"
Dynamic: license-file
